anyqats/__init__.py
anyqats/__main__.py
anyqats/cli.py
anyqats/motions.py
anyqats/signal.py
anyqats/ts.py
anyqats/tsdb.py
anyqats/app/__init__.py
anyqats/app/__main__.py
anyqats/app/exceptions.py
anyqats/app/funcs.py
anyqats/app/gui.py
anyqats/app/logger.py
anyqats/app/threading.py
anyqats/app/widgets.py
anyqats/fatigue/__init__.py
anyqats/fatigue/corrections.py
anyqats/fatigue/rainflow.py
anyqats/fatigue/sn.py
anyqats/io/__init__.py
anyqats/io/acis_sat_converter.py
anyqats/io/csv.py
anyqats/io/direct_access.py
anyqats/io/other.py
anyqats/io/pickle_format.py
anyqats/io/sima.py
anyqats/io/sima_h5.py
anyqats/io/sintef_mat.py
anyqats/io/tdms.py
anyqats/stats/__init__.py
anyqats/stats/empirical.py
anyqats/stats/gumbel.py
anyqats/stats/gumbelmin.py
anyqats/stats/weibull.py
anytimes/__init__.py
anytimes/__main__.py
anytimes/anytimes_gui.py
anytimes/evm.py
anytimes/gui/__init__.py
anytimes/gui/editor.py
anytimes/gui/evm_window.py
anytimes/gui/evs_pyextremes.py
anytimes/gui/file_loader.py
anytimes/gui/layout_utils.py
anytimes/gui/orcaflex_selector.py
anytimes/gui/sortable_table_widget_item.py
anytimes/gui/stats_dialog.py
anytimes/gui/utils.py
anytimes/gui/variable_tab.py
anytimes-0.4.0.dist-info/licenses/LICENSE
anytimes-0.4.0.dist-info/METADATA
anytimes-0.4.0.dist-info/WHEEL
anytimes-0.4.0.dist-info/entry_points.txt
anytimes-0.4.0.dist-info/top_level.txt
anytimes-0.4.0.dist-info/RECORD
