Metadata-Version: 2.4
Name: anytimes
Version: 0.4.0
Summary: PySide6-based interface for exploring and editing time-series data.
Author: AnyTimes Developers
License: MIT License
Project-URL: Homepage, https://github.com/example/anytimes
Requires-Python: >=3.8
License-File: LICENSE
Requires-Dist: numpy
Requires-Dist: pandas
Requires-Dist: openpyxl
Requires-Dist: scipy
Requires-Dist: PySide6
Requires-Dist: matplotlib
Requires-Dist: pyextremes
Dynamic: license-file
